dcs_client/__init__.py
dcs_client/client.py
dcs_client/exceptions.py
dcs_client_jer_project-0.1.1.dist-info/METADATA
dcs_client_jer_project-0.1.1.dist-info/WHEEL
dcs_client_jer_project-0.1.1.dist-info/top_level.txt
dcs_client_jer_project-0.1.1.dist-info/RECORD
