Metadata-Version: 2.4
Name: dcs-client-jer-project
Version: 0.1.1
Summary: Python client for Data Contract Standardizer
Requires-Python: >=3.7
Requires-Dist: requests>=2.25.0
Requires-Dist: pydantic>=1.8.0
Provides-Extra: dev
Requires-Dist: pytest; extra == "dev"
Requires-Dist: black; extra == "dev"
Requires-Dist: isort; extra == "dev"
